moreman/__init__.py
moreman/arghex.py
moreman/main.py
moreman-0.3.3.dist-info/LICENSE
moreman-0.3.3.dist-info/METADATA
moreman-0.3.3.dist-info/WHEEL
moreman-0.3.3.dist-info/entry_points.txt
moreman-0.3.3.dist-info/top_level.txt
moreman-0.3.3.dist-info/RECORD
