Metadata-Version: 2.1
Name: moreman
Version: 0.3.3
Summary: Man Pages for Commands without Man Pages
Home-page: https://github.com/halloleo/moreman
Author: halloleo
Author-email: moreman@halloleo.hailmail.net
License: License :: OSI Approved :: GNU General Public License v3 (GPLv3)
Keywords: system,man,help
Classifier: Programming Language :: Python
Classifier: Programming Language :: Python :: 3
Classifier: Programming Language :: Python :: Implementation :: CPython
Classifier: Development Status :: 5 - Production/Stable
Classifier: Environment :: Console
Classifier: Intended Audience :: Developers
Classifier: Natural Language :: English
Classifier: Operating System :: MacOS :: MacOS X
Classifier: Operating System :: POSIX
Classifier: Operating System :: Unix
Classifier: Topic :: System :: Shells
Classifier: Topic :: Terminals
Classifier: Topic :: Text Editors :: Emacs
Classifier: Topic :: Utilities
Requires-Python: >=3.6
License-File: LICENSE
Requires-Dist: argh ==0.26.2
